{
  "enquiry": {
    "date": "2018-02-02T10:39:46.277Z",
    "author": {
      "name": "string",
      "id": "string",
      "identifier": {
        "scheme": "string",
        "id": "string",
        "legalName": "string",
        "uri": "string"
      },
      "address": {
        "streetAddress": "string",
        "locality": "string",
        "region": "string",
        "postalCode": "string",
        "countryName": "string"
      },
      "additionalIdentifiers": [
        {
          "scheme": "string",
          "id": "string",
          "legalName": "string",
          "uri": "string"
        }
      ],
      "contactPoint": {
        "name": "string",
        "email": "string",
        "telephone": "string",
        "faxNumber": "string",
        "url": "string"
      }
    },
    "title": "string",
    "description": "string",
    "relatedItem": "string",
    "relatedLot": "string",
    "answer": "string"
  }
}
