{
  "award": {
    "id": "55951093-ab61-11e8-81c5-8d7564ebb12d",
    "date": "2018-08-29T09:25:45Z",
    "status": "pending",
    "statusDetails": "active",
    "value": {
      "amount": 150.00,
      "currency": "MDL"
    },
    "relatedLots": [
      "225b7f12-ab5d-11e8-98a2-6f3f096d14ac"
    ],
    "relatedBid": "ff578a10-ab5f-11e8-a774-c56f31395882",
    "suppliers": [
      {
        "id": "MD-IDNO-j1jj4",
        "name": "ijj0",
        "identifier": {
          "id": "j1jj4",
          "scheme": "MD-IDNO",
          "legalName": "441",
          "uri": "pj1241kpoi"
        },
        "address": {
          "streetAddress": "rrfhgsfrdg",
          "addressDetails": {
            "country": {
              "scheme": "iso-alpha2",
              "id": "MD",
              "description": "MOLDOVA",
              "uri": "http://reference.iatistandard.org"
            },
            "region": {
              "scheme": "CUATM",
              "id": "1700000",
              "description": "Cahul",
              "uri": "http://statistica.md"
            },
            "locality": {
              "scheme": "hfhfhf",
              "id": "00",
              "description": "hnhn"
            }
          }
        },
        "additionalIdentifiers": [
          {
            "id": "chh",
            "scheme": "r121g",
            "legalName": "ch",
            "uri": "hc"
          }
        ],
        "contactPoint": {
          "name": "nhnh",
          "email": "nhnhn",
          "telephone": "hnhn",
          "url": "hnhn"
        },
        "details": {
          "scale": "sme"
        }
      }
    ],
    "documents": []
  },
  "awardStatusDetails": "active",
  "bidId": "ff578a10-ab5f-11e8-a774-c56f31395882",
  "lotId": "225b7f12-ab5d-11e8-98a2-6f3f096d14ac",
  "lotAwarded": true,
  "lot": {
    "id": "225b7f12-ab5d-11e8-98a2-6f3f096d14ac",
    "title": "lot2",
    "description": "2",
    "status": "active",
    "statusDetails": "awarded",
    "value": {
      "amount": 200.00,
      "currency": "MDL"
    },
    "options": [
      {
        "hasOptions": false
      }
    ],
    "recurrentProcurement": [
      {
        "isRecurrent": false
      }
    ],
    "renewals": [
      {
        "hasRenewals": false
      }
    ],
    "variants": [
      {
        "hasVariants": false
      }
    ],
    "contractPeriod": {
      "startDate": "2018-10-20T12:40:00Z",
      "endDate": "2018-11-24T12:00:00Z"
    },
    "placeOfPerformance": {
      "address": {
        "streetAddress": "Steet",
        "postalCode": "5",
        "addressDetails": {
          "country": {
            "scheme": "iso-alpha2",
            "id": "MD",
            "description": "MOLDOVA",
            "uri": "http://reference.iatistandard.org"
          },
          "region": {
            "scheme": "CUATM",
            "id": "0301000",
            "description": "mun.Bălţi",
            "uri": "http://statistica.md"
          },
          "locality": {
            "scheme": "CUATM",
            "id": "0301000",
            "description": "mun.Bălţi",
            "uri": "http://statistica.md"
          }
        }
      },
      "description": "decr"
    }
  },
  "bid": {
    "id": "ff578a10-ab5f-11e8-a774-c56f31395882",
    "date": "2018-08-29T09:25:45Z",
    "status": "pending",
    "statusDetails": "valid",
    "tenderers": [
      {
        "id": "MD-IDNO-j1jj4",
        "name": "ijj0",
        "identifier": {
          "id": "j1jj4",
          "scheme": "MD-IDNO",
          "legalName": "441",
          "uri": "pj1241kpoi"
        },
        "address": {
          "streetAddress": "rrfhgsfrdg",
          "addressDetails": {
            "country": {
              "scheme": "iso-alpha2",
              "id": "MD",
              "description": "MOLDOVA",
              "uri": "http://reference.iatistandard.org"
            },
            "region": {
              "scheme": "CUATM",
              "id": "1700000",
              "description": "Cahul",
              "uri": "http://statistica.md"
            },
            "locality": {
              "scheme": "hfhfhf",
              "id": "00",
              "description": "hnhn"
            }
          }
        },
        "additionalIdentifiers": [
          {
            "id": "chh",
            "scheme": "r121g",
            "legalName": "ch",
            "uri": "hc"
          }
        ],
        "contactPoint": {
          "name": "nhnh",
          "email": "nhnhn",
          "telephone": "hnhn",
          "url": "hnhn"
        },
        "details": {
          "scale": "sme"
        }
      }
    ],
    "value": {
      "amount": 150.00,
      "currency": "MDL"
    },
    "documents": [
      {
        "id": "28fc73f0-a127-11e8-941f-116f5508f313",
        "documentType": "submissionDocuments",
        "relatedLots": [
          "225b7f12-ab5d-11e8-98a2-6f3f096d14ac"
        ]
      }
    ],
    "relatedLots": [
      "225b7f12-ab5d-11e8-98a2-6f3f096d14ac"
    ]
  }
}